MANIFEST.in
setup.py
Flask_Ink.egg-info/PKG-INFO
Flask_Ink.egg-info/SOURCES.txt
Flask_Ink.egg-info/dependency_links.txt
Flask_Ink.egg-info/not-zip-safe
Flask_Ink.egg-info/requires.txt
Flask_Ink.egg-info/top_level.txt
flask_ink/__init__.py
flask_ink/assets.py
flask_ink/ink.py
flask_ink/tests.py
flask_ink/__pycache__/assets.cpython-35.pyc
flask_ink/__pycache__/ink.cpython-35.pyc
flask_ink/static/css/ink-ie7.css
flask_ink/static/css/ink-ie7.min.css
flask_ink/static/css/ink.css
flask_ink/static/css/ink.min.css
flask_ink/static/font/FontAwesome.otf
flask_ink/static/font/fontawesome-webfont.eot
flask_ink/static/font/fontawesome-webfont.svg
flask_ink/static/font/fontawesome-webfont.ttf
flask_ink/static/font/fontawesome-webfont.woff
flask_ink/static/font/ubuntu-b-webfont.eot
flask_ink/static/font/ubuntu-b-webfont.svg
flask_ink/static/font/ubuntu-b-webfont.ttf
flask_ink/static/font/ubuntu-b-webfont.woff
flask_ink/static/font/ubuntu-bi-webfont.eot
flask_ink/static/font/ubuntu-bi-webfont.svg
flask_ink/static/font/ubuntu-bi-webfont.ttf
flask_ink/static/font/ubuntu-bi-webfont.woff
flask_ink/static/font/ubuntu-c-webfont.eot
flask_ink/static/font/ubuntu-c-webfont.svg
flask_ink/static/font/ubuntu-c-webfont.ttf
flask_ink/static/font/ubuntu-c-webfont.woff
flask_ink/static/font/ubuntu-l-webfont.eot
flask_ink/static/font/ubuntu-l-webfont.svg
flask_ink/static/font/ubuntu-l-webfont.ttf
flask_ink/static/font/ubuntu-l-webfont.woff
flask_ink/static/font/ubuntu-li-webfont.eot
flask_ink/static/font/ubuntu-li-webfont.svg
flask_ink/static/font/ubuntu-li-webfont.ttf
flask_ink/static/font/ubuntu-li-webfont.woff
flask_ink/static/font/ubuntu-m-webfont.eot
flask_ink/static/font/ubuntu-m-webfont.svg
flask_ink/static/font/ubuntu-m-webfont.ttf
flask_ink/static/font/ubuntu-m-webfont.woff
flask_ink/static/font/ubuntu-mi-webfont.eot
flask_ink/static/font/ubuntu-mi-webfont.svg
flask_ink/static/font/ubuntu-mi-webfont.ttf
flask_ink/static/font/ubuntu-mi-webfont.woff
flask_ink/static/font/ubuntu-r-webfont.eot
flask_ink/static/font/ubuntu-r-webfont.svg
flask_ink/static/font/ubuntu-r-webfont.ttf
flask_ink/static/font/ubuntu-r-webfont.woff
flask_ink/static/font/ubuntu-ri-webfont.eot
