Metadata-Version: 1.0
Name: Flask-Ink
Version: 3.1.10
Summary: Easily integrate Sapo Ink's framework in your Flask project.
Home-page: https://github.com/diogoosorio/flask-sapo-ink
Author: Diogo Osório
Author-email: diogo.g.osorio@gmail.com
License: MIT
Platform: any
